<NomaiObject xmlns:xsi="http://www.w3.org/2001/XMLSchema-instance" xsi:noNamespaceSchemaLocation="https://raw.githubusercontent.com/xen-42/outer-wilds-new-horizons/main/NewHorizons/Schemas/text_schema.xsd">
	
	<![CDATA[<color=orange>Excavation Site</color>]]>
	<TextBlock>
		<ID>1</ID>
		<LocationA />
		<Text>
		PHLOX: Friends! One of tentacled organisms has become beached on the shore of Statue Island following its visit to the surface! I am unable to help it without being electrified.. I request urgent assistance in aiding it before it perishes!
		</Text>
	</TextBlock>
	<TextBlock>
		<ID>2</ID>
		<LocationB />
		<ParentID>1</ParentID>
		<Text>
		DAZ: I compliment your eyes, Phlox! Give me a moment: I shall voyage there using a voyager stone, and use my voyager to safely guide it back into the waves!
		</Text>
	</TextBlock>
	<TextBlock>
		<ID>3</ID>
		<LocationA />
		<ParentID>2</ParentID>
		<Text>
		PHLOX: Daz, that was <![CDATA[<i>incredible!</i>]]> Your vessel of alloy was not phased in the slightest by the organism's terrific bioelectricity!
		</Text>
	</TextBlock>
		<TextBlock>
		<ID>4</ID>
		<ParentID>2</ParentID>
		<LocationA />
		<Text>
		PHLOX: Are there any limits at all to what the voyager is impervious to?
		</Text>
	</TextBlock>
	<TextBlock>
		<ID>5</ID>
		<ParentID>4</ParentID>
		<LocationB />
		<Text>
		DAZ: The voyager <![CDATA[<i>does</i>]]> dissolve in large bodies of water or when impacted badly.. But otherwise, it is able to weather almost any hazard it is exposed to! I have faith it will soon allow us to work remotely, from the safety of our homes.
		</Text>
	</TextBlock>
	<TextBlock>
		<ID>6</ID>
		<ParentID>5</ParentID>
		<LocationA />
		<Text>
		PHLOX: I should have known this project was a long scheme to convince Cassava to move back to the <![CDATA[<color=orange>Hanging City</color>]]> with you!
		</Text>
	</TextBlock>


<ShipLogConditions>
		<RevealFact>
			<FactID>BJelly R2</FactID>
			<Condition>1,3</Condition>
		</RevealFact>
				<RevealFact>
			<FactID>BJelly R3</FactID>
			<Condition>2</Condition>
		</RevealFact>
			<RevealFact>
			<FactID>Workshop Locked EX1</FactID>
			<Condition>5</Condition>
		</RevealFact>
	</ShipLogConditions>

</NomaiObject>