<NomaiObject xmlns:xsi="http://www.w3.org/2001/XMLSchema-instance" xsi:noNamespaceSchemaLocation="https://raw.githubusercontent.com/xen-42/outer-wilds-new-horizons/main/NewHorizons/Schemas/text_schema.xsd">
	
	<![CDATA[<color=orange>Excavation Site</color>]]>
	<TextBlock>
		<ID>1</ID>
		<LocationA />
		<Text>
		CASSAVA: I'm thrilled to be able to help with testing your new projection stone today, Daz!
		</Text>
	</TextBlock>
	<TextBlock>
		<ID>2</ID>
		<LocationB />
		<ParentID>1</ParentID>
		<Text>
		CASSAVA: To start: please let me know if you can read this message on the wall!
		</Text>
	</TextBlock>
<TextBlock>
		<ID>3</ID>
		<LocationB />
		<ParentID>2</ParentID>
		<Text>
		DAZ: I read you bright and clear, my love!
		</Text>
	</TextBlock>
	<TextBlock>
		<ID>4</ID>
		<LocationB />
		<ParentID>3</ParentID>
		<Text>
		DAZ: Next, the moment of truth... Will the voyager be able to walk beyond the projection pool?
		</Text>
	</TextBlock>
<TextBlock>
		<ID>5</ID>
		<LocationB />
		<ParentID>4</ParentID>
		<Text>
		CASSAVA: Daz? Your voyager just disappeared.. Are you alright? Daz?
		</Text>
	</TextBlock>


<ShipLogConditions>
		<RevealFact>
			<FactID>Workshop Locked EX3</FactID>
			<Condition>2</Condition>
		</RevealFact>
	</ShipLogConditions>

</NomaiObject>